Workbook

Sheet Cover
B2: GLOBAL OFFICE
B3: Three-Year Financial Model — Base Case
B5: Prepared for institutional investor review
B6: Version: 1.0 | Currency: USD | Fiscal Year: Calendar
B9: MODEL CONTENTS
B11: Assumptions — Growth, pricing, unit economics, headcount drivers
B12: Revenue — Cohort-based ARR build across three geographic tiers
B13: Cost Structure — COGS, headcount, S&M, R&D, G&A
B14: P&L Summary — GAAP income statement, EBITDA, margins
B15: Cash & Runway — Cash flow, funding rounds, cumulative burn
B16: Unit Economics — CAC, LTV, payback, magic number, Rule of 40
B17: Sensitivity — Base / Bear / Bull scenarios
... B35: Figures represent management's strategic base case and are not a forecast of actual results. All forward-looking numbers are stated assumptions; investor diligence should stress-test each driver. Global Office targets developed markets first (North America, Western Europe, UK, ANZ, Singapore, Israel), with emerging-market expansion as a secondary phase.

Sheet Assumptions
B2: ASSUMPTIONS
B3: Base case — global-first go-to-market, developed markets primary
B5: Driver | C5: Unit | D5: Year 1 | E5: Year 2 | F5: Year 3
B6: Customer Growth
B7: Paying organizations (end of year) | C7: orgs | D7: 120 | E7: 900 | F7: 3600
B8: Organic / inbound share of new logos | C8: % | D8: 0.35 | E8: 0.4 | F8: 0.45
B9: Partner channel share of new logos | C9: % | D9: 0.15 | E9: 0.25 | F9: 0.3
B10: Outbound / direct sales share | C10: % | D10: 0.5 | E10: 0.35 | F10: 0.25
B11: Gross logo churn (annual) | C11: % | D11: 0.12 | E11: 0.09 | F11: 0.07
B12: Net revenue retention | C12: % | D12: 1.05 | E12: 1.1 | F12: 1.15
B14: Pricing
B15: Blended ARPU per org per month | C15: USD | D15: 220 | E15: 260 | F15: 300
B16: Enterprise share of new bookings | C16: % | D16: 0.1 | E16: 0.18 | F16: 0.28
B17: Annual price increase (existing base) | C17: % | D17: 0 | E17: 0.05 | F17: 0.07
B19: Unit Economics
B20: Blended CAC per org | C20: USD | D20: 1400 | E20: 1250 | F20: 1150
B21: Gross margin | C21: % | D21: 0.72 | E21: 0.76 | F21: 0.8
B22: Sales & Marketing (% of revenue) | C22: % | D22: 1.2 | E22: 0.65 | F22: 0.42
B23: R&D (% of revenue) | C23: % | D23: 0.85 | E23: 0.55 | F23: 0.35
B24: G&A (% of revenue) | C24: % | D24: 0.4 | E24: 0.25 | F24: 0.18
B26: Headcount (end of year)
B27: Engineering | C27: FTE | D27: 6 | E27: 14 | F27: 28
B28: Product & Design | C28: FTE | D28: 2 | E28: 5 | F28: 9
B29: Sales & Marketing | C29: FTE | D29: 4 | E29: 12 | F29: 26
B30: Customer Success & Support | C30: FTE | D30: 2 | E30: 7 | F30: 18
B31: G&A / Operations | C31: FTE | D31: 2 | E31: 4 | F31: 7
B32: Fully-loaded cost per FTE (blended) | C32: USD/yr | D32: 95000 | E32: 105000 | F32: 115000
B34: Capital
B35: Pre-seed raise (close in Y1) | C35: USD | D35: 1500000 | E35: 0 | F35: 0
B36: Seed raise (close in Y2) | C36: USD | D36: 0 | E36: 5000000 | F36: 0
B37: Series A (close in Y3) | C37: USD | D37: 0 | E37: 0 | F37: 15000000
B38: Opening cash (Y1) | C38: USD | D38: 50000 | E38: 0 | F38: 0

Sheet Revenue
B2: REVENUE BUILD
B3: ARR = ending orgs × blended ARPU × 12
B5: Line | C5: Year 1 | D5: Year 2 | E5: Year 3
B6: Ending paying organizations | C6: =Assumptions!D6 | D6: =Assumptions!E6 | E6: =Assumptions!F6
B7: Average organizations (avg of BoP/EoP) | C7: =(0+C6)/2 | D7: =(C6+D6)/2 | E7: =(D6+E6)/2
B8: Blended ARPU (monthly, USD) | C8: =Assumptions!D14 | D8: =Assumptions!E14 | E8: =Assumptions!F14
B9: MRR (end of year) | C9: =C6*C8 | D9: =D6*D8 | E9: =E6*E8
B10: ARR (end of year) | C10: =C9*12 | D10: =D9*12 | E10: =E9*12
B11: Recognized revenue (avg orgs × ARPU × 12) | C11: =C7*C8*12 | D11: =D7*D8*12 | E11: =E7*E8*12
B13: YoY revenue growth | D13: =D11/C11-1 | E13: =E11/D11-1

Sheet Cost Structure
B2: COST STRUCTURE
B5: Line | C5: Year 1 | D5: Year 2 | E5: Year 3
B6: Recognized revenue | C6: =Revenue!C11 | D6: =Revenue!D11 | E6: =Revenue!E11
B7: Gross margin % | C7: =Assumptions!D20 | D7: =Assumptions!E20 | E7: =Assumptions!F20
B8: COGS | C8: =C6*(1-C7) | D8: =D6*(1-D7) | E8: =E6*(1-E7)
B9: Gross profit | C9: =C6-C8 | D9: =D6-D8 | E9: =E6-E8
B11: Total FTE (end of year) | C11: =SUM(Assumptions!D26:D30) | D11: =SUM(Assumptions!E26:E30) | E11: =SUM(Assumptions!F26:F30)
B12: Avg FTE (avg of BoP/EoP) | C12: =(0+C11)/2 | D12: =(C11+D11)/2 | E12: =(D11+E11)/2
B13: Fully-loaded cost per FTE | C13: =Assumptions!D31 | D13: =Assumptions!E31 | E13: =Assumptions!F31
B14: Total personnel cost | C14: =C12*C13 | D14: =D12*D13 | E14: =E12*E13
B16: S&M (% of revenue) | C16: =Assumptions!D21 | D16: =Assumptions!E21 | E16: =Assumptions!F21
B17: S&M expense | C17: =C6*C16 | D17: =D6*D16 | E17: =E6*E16
B18: R&D (% of revenue) | C18: =Assumptions!D22 | D18: =Assumptions!E22 | E18: =Assumptions!F22
B19: R&D expense | C19: =C6*C18 | D19: =D6*D18 | E19: =E6*E18
B20: G&A (% of revenue) | C20: =Assumptions!D23 | D20: =Assumptions!E23 | E20: =Assumptions!F23
B21: G&A expense | C21: =C6*C20 | D21: =D6*D20 | E21: =E6*E20
B23: Total opex (excl. COGS) | C23: =C17+C19+C21 | D23: =D17+D19+D21 | E23: =E17+E19+E21

Sheet P&L Summary
B2: INCOME STATEMENT
B5: Line | C5: Year 1 | D5: Year 2 | E5: Year 3
B6: Revenue | C6: =Revenue!C11 | D6: =Revenue!D11 | E6: =Revenue!E11
B7: COGS | C7: =-'Cost Structure'!C8 | D7: =-'Cost Structure'!D8 | E7: =-'Cost Structure'!E8
B8: Gross profit | C8: =C6+C7 | D8: =D6+D7 | E8: =E6+E7
B9: Gross margin % | C9: =C8/C6 | D9: =D8/D6 | E9: =E8/E6
B11: S&M | C11: =-'Cost Structure'!C17 | D11: =-'Cost Structure'!D17 | E11: =-'Cost Structure'!E17
B12: R&D | C12: =-'Cost Structure'!C19 | D12: =-'Cost Structure'!D19 | E12: =-'Cost Structure'!E19
B13: G&A | C13: =-'Cost Structure'!C21 | D13: =-'Cost Structure'!D21 | E13: =-'Cost Structure'!E21
B14: Total opex | C14: =SUM(C11:C13) | D14: =SUM(D11:D13) | E14: =SUM(E11:E13)
B16: EBITDA | C16: =C8+C14 | D16: =D8+D14 | E16: =E8+E14
B17: EBITDA margin % | C17: =C16/C6 | D17: =D16/D6 | E17: =E16/E6
B18: Rule of 40 (Growth % + EBITDA %) | C18: =IF(C6=0,0,0) | D18: =(D6/C6-1)+D17 | E18: =(E6/D6-1)+E17

Sheet Cash & Runway
B2: CASH & RUNWAY
B3: Simplified cash flow — assumes ~30-day working capital drag, no capex
B5: Line | C5: Year 1 | D5: Year 2 | E5: Year 3
B6: Opening cash | C6: =Assumptions!D34 | D6: =C11 | E6: =D11
B7: EBITDA | C7: ='P&L Summary'!C16 | D7: ='P&L Summary'!D16 | E7: ='P&L Summary'!E16
B8: Working capital change (est.) | C8: =-'P&L Summary'!C6*0.08 | D8: =-'P&L Summary'!D6*0.08 | E8: =-'P&L Summary'!E6*0.08
B9: New capital raised | C9: =SUM(Assumptions!D32:D34) | D9: =SUM(Assumptions!E32:E34) | E9: =SUM(Assumptions!F32:F34)
B10: Net cash movement | C10: =C7+C8+C9 | D10: =D7+D8+D9 | E10: =E7+E8+E9
B11: Closing cash | C11: =C6+C10 | D11: =D6+D10 | E11: =E6+E10
B13: Cash runway at year-end (months, at trailing burn) | C13: =IF(C7>=0,"cash-flow positive",C11/(-C7/12)) | D13: =IF(D7>=0,"cash-flow positive",D11/(-D7/12)) | E13: =IF(E7>=0,"cash-flow positive",E11/(-E7/12))

Sheet Unit Economics
B2: UNIT ECONOMICS
B5: Metric | C5: Year 1 | D5: Year 2 | E5: Year 3
B6: Blended ARPU (annual) | C6: =Assumptions!D14*12 | D6: =Assumptions!E14*12 | E6: =Assumptions!F14*12
B7: Gross margin | C7: =Assumptions!D20 | D7: =Assumptions!E20 | E7: =Assumptions!F20
B8: Gross profit per org | C8: =C6*C7 | D8: =D6*D7 | E8: =E6*E7
B9: Gross logo churn | C9: =Assumptions!D11 | D9: =Assumptions!E11 | E9: =Assumptions!F11
B10: Implied customer life (yrs) | C10: =1/C9 | D10: =1/D9 | E10: =1/E9
B11: LTV (gross-margin adjusted) | C11: =C8*C10 | D11: =D8*D10 | E11: =E8*E10
B12: Blended CAC | C12: =Assumptions!D19 | D12: =Assumptions!E19 | E12: =Assumptions!F19
B13: LTV : CAC | C13: =C11/C12 | D13: =D11/D12 | E13: =E11/E12
B14: CAC payback (months) | C14: =C12/(C6*C7/12) | D14: =D12/(D6*D7/12) | E14: =E12/(E6*E7/12)
B15: Net revenue retention | C15: =Assumptions!D12 | D15: =Assumptions!E12 | E15: =Assumptions!F12

Sheet Sensitivity
B2: SCENARIO SENSITIVITY
B3: Illustrative bear / base / bull outcomes for Year 3 ARR
B5: Scenario | C5: Y3 Orgs | D5: Y3 ARPU/mo | E5: Y3 ARR | F5: Y3 GM % | G5: Y3 EBITDA % | H5: Y3 EBITDA
B6: Bear | C6: 1800 | D6: 240 | E6: =C6*D6*12 | F6: 0.72 | G6: -0.15 | H6: =E6*G6
B7: Base | C7: 3600 | D7: 300 | E7: =C7*D7*12 | F7: 0.8 | G7: 0.05 | H7: =E7*G7
B8: Bull | C8: 5500 | D8: 340 | E8: =C8*D8*12 | F8: 0.83 | G8: 0.15 | H8: =E8*G8
B11: Interpretation
B12: Bear reflects a slower developed-market ramp with weaker enterprise mix. Base is management's plan. Bull assumes earlier enterprise traction and partner acceleration in Y2–Y3.

Sheet Sources
B2: SOURCES & BENCHMARKS
B5: Claim / Benchmark | C5: Source | D5: Date
B6: SMB SaaS gross logo churn 5–15% | C6: KeyBanc Capital Markets — SaaS Survey | D6: 2024
B7: Median SaaS gross margin 72–80% | C7: SaaStr / OpenView SaaS Benchmarks | D7: 2024
B8: Rule of 40 as investor benchmark | C8: Bessemer State of the Cloud | D8: 2024
B9: Global work management TAM | C9: IDC / Gartner Digital Workplace | D9: 2024
B10: AI operations software growth | C10: McKinsey State of AI | D10: 2024
B11: SMB software spend by region | C11: Gartner Enterprise Software Forecast | D11: 2024
B12: SaaS blended CAC payback benchmarks | C12: OpenView Expansion SaaS Benchmarks | D12: 2024
B13: NRR by ACV band | C13: SaaS Capital SaaS Metrics Report | D13: 2024
